minty_infra_email/__init__.py
minty_infra_email/infrastructure.py
minty_infra_email/py.typed
minty_infra_email-2.0.2.dist-info/METADATA
minty_infra_email-2.0.2.dist-info/WHEEL
minty_infra_email-2.0.2.dist-info/top_level.txt
minty_infra_email-2.0.2.dist-info/RECORD
