Metadata-Version: 2.1
Name: minty-infra-email
Version: 2.0.2
Summary: Infrastructure class for sending email
Home-page: https://gitlab.com/minty-python/minty-infra-email
Author: Martijn van de Streek
Author-email: martijn@mintlab.nl
License: EUPL license
Keywords: minty_infra_email
Platform: UNKNOWN
Classifier: Development Status :: 5 - Production/Stable
Classifier: Intended Audience :: Developers
Classifier: License :: OSI Approved :: European Union Public Licence 1.2 (EUPL 1.2)
Classifier: Natural Language :: English
Classifier: Programming Language :: Python :: 3.9
Requires-Dist: minty (~=3.0)
